are_you_sure/__init__.py
are_you_sure-1.0.2.dist-info/METADATA
are_you_sure-1.0.2.dist-info/RECORD
are_you_sure-1.0.2.dist-info/WHEEL
are_you_sure-1.0.2.dist-info/top_level.txt
