Metadata-Version: 2.1
Name: are-you-sure
Version: 1.0.2
Summary: Simple decorator to check before running
Home-page: https://github.com/simonwardjones/are_you_sure
Author: Simon Ward-Jones
Author-email: simonwardjones16@gmail.com
License: MIT
Platform: UNKNOWN
Classifier: License :: OSI Approved :: MIT License
Classifier: Programming Language :: Python :: 3
Classifier: Programming Language :: Python
